normas/__init__.py
normas/decreto_estadual_8468.py
normas/run.py
normas/data/tab_dec_8468.xlsx
decreto_estadual_8468-1.1.6.dist-info/LICENSE
decreto_estadual_8468-1.1.6.dist-info/METADATA
decreto_estadual_8468-1.1.6.dist-info/WHEEL
decreto_estadual_8468-1.1.6.dist-info/top_level.txt
decreto_estadual_8468-1.1.6.dist-info/RECORD
