Metadata-Version: 2.1
Name: decreto-estadual-8468
Version: 1.1.6
Summary: O projeto objetiva disponibilizar os parâmetros de qualidade em formato adequado para utilização em análises computacionais
Home-page: https://github.com/gaemapiracicaba/norma_dec_8468-76
Author: Michel Metran
Author-email: michelmetran@gmail.com
License: UNKNOWN
Keywords: python,water,water-quality,water-resources
Platform: UNKNOWN
Classifier: Programming Language :: Python :: 3
Classifier: License :: OSI Approved :: MIT License
Classifier: Operating System :: OS Independent
Classifier: Natural Language :: Portuguese
Classifier: Intended Audience :: Developers
Requires-Python: >=3
License-File: LICENSE
Requires-Dist: pandas (>=1.0.0)
Requires-Dist: openpyxl (>=3.0.0)
